aisuite_async/__init__.py
aisuite_async/async_client.py
aisuite_async/base_client.py
aisuite_async/client.py
aisuite_async/framework/__init__.py
aisuite_async/framework/chat_completion_response.py
aisuite_async/framework/choice.py
aisuite_async/framework/message.py
aisuite_async/framework/provider_interface.py
aisuite_async/provider.py
aisuite_async/providers/__init__.py
aisuite_async/providers/anthropic_provider.py
aisuite_async/providers/aws_provider.py
aisuite_async/providers/azure_provider.py
aisuite_async/providers/cerebras_provider.py
aisuite_async/providers/cohere_provider.py
aisuite_async/providers/deepseek_provider.py
aisuite_async/providers/fireworks_provider.py
aisuite_async/providers/google_provider.py
aisuite_async/providers/groq_provider.py
aisuite_async/providers/huggingface_provider.py
aisuite_async/providers/message_converter.py
aisuite_async/providers/mistral_provider.py
aisuite_async/providers/nebius_provider.py
aisuite_async/providers/ollama_provider.py
aisuite_async/providers/openai_provider.py
aisuite_async/providers/sambanova_provider.py
aisuite_async/providers/together_provider.py
aisuite_async/providers/watsonx_provider.py
aisuite_async/providers/xai_provider.py
aisuite_async/tool_runner.py
aisuite_async/utils/tools.py
aisuite_async-0.1.11.2.dist-info/LICENSE
aisuite_async-0.1.11.2.dist-info/METADATA
aisuite_async-0.1.11.2.dist-info/WHEEL
aisuite_async-0.1.11.2.dist-info/RECORD
