Metadata-Version: 2.3
Name: aisuite-async
Version: 0.1.11.2
Summary: Uniform access layer for LLMs with async support
Author: Andrew Ng, Rohit P, Kapulkin S
Requires-Python: >=3.10,<4.0
Classifier: Programming Language :: Python :: 3
Classifier: Programming Language :: Python :: 3.10
Classifier: Programming Language :: Python :: 3.11
Classifier: Programming Language :: Python :: 3.12
Classifier: Programming Language :: Python :: 3.13
Provides-Extra: all
Provides-Extra: anthropic
Provides-Extra: aws
Provides-Extra: azure
Provides-Extra: cerebras
Provides-Extra: cohere
Provides-Extra: deepseek
Provides-Extra: google
Provides-Extra: groq
Provides-Extra: huggingface
Provides-Extra: mistral
Provides-Extra: ollama
Provides-Extra: openai
Provides-Extra: watsonx
Requires-Dist: anthropic (>=0.30.1,<0.31.0) ; extra == "anthropic" or extra == "all"
Requires-Dist: boto3 (>=1.34.144,<2.0.0) ; extra == "aws"
Requires-Dist: cerebras_cloud_sdk (>=1.19.0,<2.0.0) ; extra == "cerebras" or extra == "all"
Requires-Dist: cohere (>=5.12.0,<6.0.0) ; extra == "cohere" or extra == "all"
Requires-Dist: groq (>=0.9.0,<0.10.0) ; extra == "groq" or extra == "all"
Requires-Dist: httpx (>=0.28.1,<0.29.0)
Requires-Dist: ibm-watsonx-ai (>=1.1.16,<2.0.0) ; extra == "watsonx"
Requires-Dist: mistralai (>=1.0.3,<2.0.0) ; extra == "mistral"
Requires-Dist: openai (>=1.35.8,<2.0.0) ; extra == "deepseek" or extra == "openai" or extra == "all"
Requires-Dist: vertexai (>=1.63.0,<2.0.0) ; extra == "google"
